marimo_labs/__init__.py
marimo_labs/huggingface/__init__.py
marimo_labs/huggingface/_client_utils.py
marimo_labs/huggingface/_load.py
marimo_labs/huggingface/_load_utils.py
marimo_labs/huggingface/_outputs.py
marimo_labs/huggingface/_processing_utils.py
marimo_labs-0.1.0.dist-info/METADATA
marimo_labs-0.1.0.dist-info/WHEEL
marimo_labs-0.1.0.dist-info/top_level.txt
marimo_labs-0.1.0.dist-info/RECORD
