Metadata-Version: 2.1
Name: marimo_labs
Version: 0.1.0
Summary: Cutting-edge experimental features for marimo
Project-URL: homepage, https://github.com/marimo-team/marimo_labs
Classifier: Operating System :: OS Independent
Classifier: License :: OSI Approved :: Apache Software License
Classifier: Environment :: Console
Classifier: Environment :: Web Environment
Classifier: Intended Audience :: Developers
Classifier: Intended Audience :: Science/Research
Classifier: Intended Audience :: Education
Classifier: Programming Language :: Python
Classifier: Programming Language :: Python :: 3.8
Classifier: Programming Language :: Python :: 3.9
Classifier: Programming Language :: Python :: 3.10
Classifier: Programming Language :: Python :: 3.11
Classifier: Programming Language :: Python :: 3 :: Only
Requires-Python: >=3.8
Requires-Dist: marimo >=0.3.8
Requires-Dist: huggingface-hub >=0.19.3
Requires-Dist: requests >=2.0
Requires-Dist: pyyaml >=5.0
Requires-Dist: Pillow >=7.0
Requires-Dist: numpy >=1.21.0
Provides-Extra: dev
Requires-Dist: black ~=23.3.0 ; extra == 'dev'
Requires-Dist: build ~=0.10.0 ; extra == 'dev'
Requires-Dist: mypy ~=1.9.0 ; extra == 'dev'
Requires-Dist: ruff ~=0.3.5 ; extra == 'dev'
Requires-Dist: typos ~=1.20.4 ; extra == 'dev'
Requires-Dist: pytest ~=8.1.1 ; extra == 'dev'
